paulicirc/__init__.py
paulicirc/builders.py
paulicirc/circuits.py
paulicirc/gadgets.py
paulicirc/layers.py
paulicirc/py.typed
paulicirc/utils/__init__.py
paulicirc/utils/numpy.py
paulicirc/utils/options.py
paulicirc-0.2.0.dist-info/METADATA
paulicirc-0.2.0.dist-info/WHEEL
paulicirc-0.2.0.dist-info/licenses/LICENSE
paulicirc-0.2.0.dist-info/RECORD
