Metadata-Version: 2.3
Name: paulicirc
Version: 0.2.0
Summary: A library for quantum circuits based on Pauli gadgets.
Project-URL: Documentation, https://paulicirc.readthedocs.io
Project-URL: Repository, https://github.com/neverlocal/paulicirc
Project-URL: Issues, https://github.com/neverlocal/paulicirc/issues
Author: NeverLocal
License: LGPL-3.0
Classifier: Development Status :: 3 - Alpha
Classifier: Natural Language :: English
Classifier: Operating System :: OS Independent
Classifier: Programming Language :: Python :: 3
Classifier: Programming Language :: Python :: 3.10
Classifier: Programming Language :: Python :: 3.11
Classifier: Programming Language :: Python :: 3.12
Classifier: Programming Language :: Python :: 3.13
Classifier: Typing :: Typed
Requires-Python: >=3.10
Requires-Dist: euler>=1.0.2.post0
Requires-Dist: numba>=0.61.2
Requires-Dist: numpy>=2.2.6
Requires-Dist: optmanage>=1.1.1
Requires-Dist: scipy>=1.14.1
Requires-Dist: typing-validation>=1.2.12
